package/__init__.py
package_tesst_as030pc-0.3.dist-info/LICENSE.txt
package_tesst_as030pc-0.3.dist-info/METADATA
package_tesst_as030pc-0.3.dist-info/WHEEL
package_tesst_as030pc-0.3.dist-info/top_level.txt
package_tesst_as030pc-0.3.dist-info/RECORD
