Metadata-Version: 2.1
Name: package-tesst-as030pc
Version: 0.3
Summary: <Basic desc>
Home-page: UNKNOWN
Author: Andres Palma
Author-email: palma.castaneda030@gmail.com
License: UNKNOWN
Platform: UNKNOWN
Classifier: Programming Language :: Python :: 3
Classifier: License :: OSI Approved :: MIT License
Classifier: Operating System :: OS Independent
